{"metadata":{"dataVersion":"2","matchId":"EUW1_6133694173","participants":["DvybAkC-qvNEWUPq9CgCdYkIsqa9xUvyGh-uvZxBKbnNQCQgw-5fPRf4By2q_xLyo7glS4AI9YcVTg","YOqYLYrvcDcUwmtPr8pbdueWlKAmR7L5hf9whqVhWRiI1r-APuKmYs6fj4BXihErar7oM9bx8ohPMA","QWFRN5F1plRJavwMotH0klv3JEQFkXQ_WO_Ronhi6CY9XrPf_rIMJiMhSE5EL5cYR7Cfn8kQSkzyLA","uGEzT6chd6zFfSEYVmiv6d-zEPgFlrwzRHpZlWzNk9BvMf_NCVtu2u_Msxtj_lggVlpRdDQTw07GYg","_Xsx3gnqgOXgqr583lUsxGdp51yJn4J4vmlHIZHq_gBVBOwHJcf-sP7t40Yk1faH4uxfC7Bt2vo42Q","qhQcyLEC26FRmtUCKdc24ErrxadSAz-tasWjqoNXaLSWPKy0lCV9zJLlejDVeqkZHdFSpnG-Gzoabg","D3-txI8fd4LnzH-6e36fZjRsz4_2PPgW9VThsvPTMwvRu5oQE7DBXm991TkegKqcGkmqjoAFkRS_QQ","nGVbXWThRhM1jk6MzeAa-0ULFRQBRoSFSXLty8aWR8KipJ2-w82FRTaJHs38TWCpUCgHzbR4b03S9A","gunnoWXJDEoUg0UbOCWMN1AuSQ-2YJvBFKwJjVYOEJ9oeC1091F37FeVzCvRZBzPGG-q6py1bGq6Bw","9Z1JFDSeOnHsvZC0DIAWh_wP3XkdZiHYy_yf8vxIOHS29gol_x4z7_DiCzjbnxao5Wqp5fnPzm6LfQ"]},"info":{"gameCreation":1667350577947,"gameDuration":2188,"gameEndTimestamp":1667352803523,"gameId":6133694173,"gameMode":"CLASSIC","gameName":"teambuilder-match-6133694173","gameStartTimestamp":1667350614643,"gameType":"MATCHED_GAME","gameVersion":"12.20.474.8882","mapId":11,"participants":[{"assists":4,"baronKills":0,"basicPings":36,"bountyLevel":0,"challenges":{"12AssistStreakCount":0,"abilityUses":280,"acesBefore15Minutes":0,"alliedJungleMonsterKills":5.500000029802322,"baronTakedowns":0,"blastConeOppositeOpponentCount":0,"bountyGold":675,"buffsStolen":0,"completeSupportQuestInTime":0,"controlWardTimeCoverageInRiverOrEnemyHalf":0.402809903119263,"controlWardsPlaced":6,"damagePerMinute":706.4125259576812,"damageTakenOnTeamPercentage":0.1956845799754934,"dancedWithRiftHerald":0,"deathsByEnemyChamps":11,"dodgeSkillShotsSmallWindow":12,"doubleAces":0,"dragonTakedowns":1,"earliestDragonTakedown":1859.0609152956542,"earliestElderDragon":1859.0609152956542,"earlyLaningPhaseGoldExpAdvantage":0,"effectiveHealAndShielding":0,"elderDragonKillsWithOpposingSoul":1,"elderDragonMultikills":0,"enemyChampionImmobilizations":1,"enemyJungleMonsterKills":0,"epicMonsterKillsNearEnemyJungler":0,"epicMonsterKillsWithin30SecondsOfSpawn":0,"epicMonsterSteals":0,"epicMonsterStolenWithoutSmite":0,"firstTurretKilledTime":671.7035906723263,"flawlessAces":0,"fullTeamTakedown":1,"gameLength":2188.924978844632,"getTakedownsInAllLanesEarlyJungleAsLaner":0,"goldPerMinute":409.4955861212833,"hadOpenNexus":0,"immobilizeAndKillWithAlly":0,"initialBuffCount":0,"initialCrabCount":0,"jungleCsBefore10Minutes":0,"junglerTakedownsNearDamagedEpicMonster":0,"kTurretsDestroyedBeforePlatesFall":0,"kda":1.1818181818181819,"killAfterHiddenWithAlly":0,"killParticipation":0.2653061224489796,"killedChampTookFullTeamDamageSurvived":0,"killingSprees":1,"killsNearEnemyTurret":1,"killsOnOtherLanesEarlyJungleAsLaner":0,"killsOnRecentlyHealedByAramPack":0,"killsUnderOwnTurret":1,"killsWithHelpFromEpicMonster":0,"knockEnemyIntoTeamAndKill":0,"landSkillShotsEarlyGame":10,"laneMinionsFirst10Minutes":59,"laningPhaseGoldExpAdvantage":0,"legendaryCount":0,"lostAnInhibitor":0,"maxCsAdvantageOnLaneOpponent":57,"maxKillDeficit":0,"maxLevelLeadLaneOpponent":1,"moreEnemyJungleThanOpponent":-143.25000008940697,"multiKillOneSpell":0,"multiTurretRiftHeraldCount":1,"multikills":1,"multikillsAfterAggressiveFlash":0,"mythicItemUsed":6630,"outerTurretExecutesBefore10Minutes":0,"outnumberedKills":3,"outnumberedNexusKill":0,"perfectDragonSoulsTaken":0,"perfectGame":0,"pickKillWithAlly":9,"playedChampSelectPosition":1,"poroExplosions":0,"quickCleanse":0,"quickFirstTurret":0,"quickSoloKills":0,"riftHeraldTakedowns":0,"saveAllyFromDeath":0,"scuttleCrabKills":0,"skillshotsDodged":65,"skillshotsHit":53,"snowballsHit":0,"soloBaronKills":0,"soloKills":1,"soloTurretsLategame":1,"stealthWardsPlaced":4,"survivedSingleDigitHpCount":0,"survivedThreeImmobilizesInFight":4,"takedownOnFirstTurret":0,"takedowns":13,"takedownsAfterGainingLevelAdvantage":0,"takedownsBeforeJungleMinionSpawn":0,"takedownsFirstXMinutes":1,"takedownsInAlcove":0,"takedownsInEnemyFountain":0,"teamBaronKills":0,"teamDamagePercentage":0.16177049414635022,"teamElderDragonKills":1,"teamRiftHeraldKills":2,"threeWardsOneSweeperCount":0,"tookLargeDamageSurvived":0,"turretPlatesTaken":0,"turretTakedowns":1,"turretsTakenWithRiftHerald":15,"twentyMinionsIn3SecondsCount":10,"unseenRecalls":0,"visionScoreAdvantageLaneOpponent":0.09772038459777832,"visionScorePerMinute":0.7181781786929085,"wardTakedowns":1,"wardTakedownsBefore20M":0,"wardsGuarded":0},"champExperience":17107,"champLevel":17,"championId":2,"championName":"Olaf","championTransform":0,"consumablesPurchased":8,"damageDealtToBuildings":3308,"damageDealtToObjectives":7438,"damageDealtToTurrets":3308,"damageSelfMitigated":51343,"deaths":11,"detectorWardsPlaced":6,"doubleKills":1,"dragonKills":0,"eligibleForProgression":true,"firstBloodAssist":false,"firstBloodKill":false,"firstTowerAssist":false,"firstTowerKill":false,"gameEndedInEarlySurrender":false,"gameEndedInSurrender":false,"goldEarned":14939,"goldSpent":14930,"individualPosition":"TOP","inhibitorKills":0,"inhibitorTakedowns":0,"inhibitorsLost":2,"item0":3053,"item1":6630,"item2":3071,"item3":6333,"item4":3047,"item5":0,"item6":3364,"itemsPurchased":32,"killingSprees":2,"kills":9,"lane":"TOP","largestCriticalStrike":0,"largestKillingSpree":6,"largestMultiKill":2,"longestTimeSpentLiving":708,"magicDamageDealt":0,"magicDamageDealtToChampions":0,"magicDamageTaken":12450,"neutralMinionsKilled":8,"nexusKills":0,"nexusLost":1,"nexusTakedowns":0,"objectivesStolen":0,"objectivesStolenAssists":0,"participantId":1,"pentaKills":0,"perks":{"statPerks":{"defense":5001,"flex":5008,"offense":5005},"styles":[{"description":"primaryStyle","selections":[{"perk":8010,"var1":404,"var2":0,"var3":0},{"perk":9111,"var1":1806,"var2":260,"var3":0},{"perk":9103,"var1":23,"var2":40,"var3":0},{"perk":8299,"var1":972,"var2":0,"var3":0}],"style":8000},{"description":"subStyle","selections":[{"perk":8410,"var1":85,"var2":0,"var3":0},{"perk":8345,"var1":3,"var2":0,"var3":0}],"style":8300}]},"physicalDamageDealt":142872,"physicalDamageDealtToChampions":15286,"physicalDamageTaken":31378,"profileIcon":1053,"puuid":"DvybAkC-qvNEWUPq9CgCdYkIsqa9xUvyGh-uvZxBKbnNQCQgw-5fPRf4By2q_xLyo7glS4AI9YcVTg","quadraKills":0,"riotIdName":"","riotIdTagline":"","role":"SOLO","sightWardsBoughtInGame":0,"spell1Casts":124,"spell2Casts":38,"spell3Casts":103,"spell4Casts":15,"summoner1Casts":8,"summoner1Id":6,"summoner2Casts":5,"summoner2Id":4,"summonerId":"3nzSIg6M6quIgX64HRFLgRLunNZhh1k0dmcW_6Qbku7El_s","summonerLevel":484,"summonerName":"Oukai","teamEarlySurrendered":false,"teamId":100,"teamPosition":"TOP","timeCCingOthers":15,"timePlayed":2188,"totalDamageDealt":173086,"totalDamageDealtToChampions":25771,"totalDamageShieldedOnTeammates":0,"totalDamageTaken":49121,"totalHeal":17676,"totalHealsOnTeammates":0,"totalMinionsKilled":210,"totalTimeCCDealt":322,"totalTimeSpentDead":323,"totalUnitsHealed":1,"tripleKills":0,"trueDamageDealt":30213,"trueDamageDealtToChampions":10484,"trueDamageTaken":5292,"turretKills":1,"turretTakedowns":1,"turretsLost":8,"unrealKills":0,"visionScore":26,"visionWardsBoughtInGame":6,"wardsKilled":1,"wardsPlaced":10,"win":false},{"assists":8,"baronKills":0,"basicPings":37,"bountyLevel":0,"challenges":{"12AssistStreakCount":0,"abilityUses":406,"acesBefore15Minutes":0,"alliedJungleMonsterKills":124.50000014901161,"baronTakedowns":0,"blastConeOppositeOpponentCount":0,"bountyGold":675,"buffsStolen":0,"completeSupportQuestInTime":0,"controlWardTimeCoverageInRiverOrEnemyHalf":0.0758629573397324,"controlWardsPlaced":3,"damagePerMinute":1420.4289557315567,"damageTakenOnTeamPercentage":0.24892504072387783,"dancedWithRiftHerald":0,"deathsByEnemyChamps":10,"dodgeSkillShotsSmallWindow":17,"doubleAces":0,"dragonTakedowns":1,"earliestDragonTakedown":1859.0609152956542,"earliestElderDragon":1859.0609152956542,"earlyLaningPhaseGoldExpAdvantage":0,"effectiveHealAndShielding":0,"elderDragonKillsWithOpposingSoul":1,"elderDragonMultikills":0,"enemyChampionImmobilizations":0,"enemyJungleMonsterKills":6.600000023841858,"epicMonsterKillsNearEnemyJungler":1,"epicMonsterKillsWithin30SecondsOfSpawn":2,"epicMonsterSteals":0,"epicMonsterStolenWithoutSmite":0,"firstTurretKilledTime":671.7035906723263,"flawlessAces":0,"fullTeamTakedown":1,"gameLength":2188.924978844632,"goldPerMinute":568.0223009658719,"hadOpenNexus":0,"immobilizeAndKillWithAlly":0,"initialBuffCount":2,"initialCrabCount":0,"jungleCsBefore10Minutes":56.15000006556511,"junglerKillsEarlyJungle":0,"junglerTakedownsNearDamagedEpicMonster":0,"kTurretsDestroyedBeforePlatesFall":1,"kda":2.5,"killAfterHiddenWithAlly":1,"killParticipation":0.5102040816326531,"killedChampTookFullTeamDamageSurvived":0,"killingSprees":3,"killsNearEnemyTurret":3,"killsOnLanersEarlyJungleAsJungler":2,"killsOnRecentlyHealedByAramPack":0,"killsUnderOwnTurret":1,"killsWithHelpFromEpicMonster":2,"knockEnemyIntoTeamAndKill":0,"landSkillShotsEarlyGame":0,"laneMinionsFirst10Minutes":13,"laningPhaseGoldExpAdvantage":0,"legendaryCount":0,"lostAnInhibitor":0,"maxCsAdvantageOnLaneOpponent":19.19999998807907,"maxKillDeficit":0,"maxLevelLeadLaneOpponent":2,"moreEnemyJungleThanOpponent":-87.10000002384186,"multiKillOneSpell":0,"multiTurretRiftHeraldCount":1,"multikills":2,"multikillsAfterAggressiveFlash":0,"mythicItemUsed":4633,"outerTurretExecutesBefore10Minutes":0,"outnumberedKills":4,"outnumberedNexusKill":0,"perfectDragonSoulsTaken":0,"perfectGame":0,"pickKillWithAlly":18,"playedChampSelectPosition":1,"poroExplosions":0,"quickCleanse":0,"quickFirstTurret":0,"quickSoloKills":2,"riftHeraldTakedowns":2,"saveAllyFromDeath":0,"scuttleCrabKills":2,"skillshotsDodged":91,"skillshotsHit":66,"snowballsHit":0,"soloBaronKills":0,"soloKills":3,"stealthWardsPlaced":1,"survivedSingleDigitHpCount":0,"survivedThreeImmobilizesInFight":4,"takedownOnFirstTurret":1,"takedowns":25,"takedownsAfterGainingLevelAdvantage":2,"takedownsBeforeJungleMinionSpawn":0,"takedownsFirstXMinutes":6,"takedownsInAlcove":0,"takedownsInEnemyFountain":0,"teamBaronKills":0,"teamDamagePercentage":0.3252823040714934,"teamElderDragonKills":1,"teamRiftHeraldKills":2,"threeWardsOneSweeperCount":0,"tookLargeDamageSurvived":0,"turretPlatesTaken":6,"turretTakedowns":7,"turretsTakenWithRiftHerald":15,"twentyMinionsIn3SecondsCount":3,"unseenRecalls":0,"visionScoreAdvantageLaneOpponent":-0.3828245997428894,"visionScorePerMinute":0.9295708690068434,"wardTakedowns":4,"wardTakedownsBefore20M":0,"wardsGuarded":1},"champExperience":19403,"champLevel":18,"championId":887,"championName":"Gwen","championTransform":0,"consumablesPurchased":5,"damageDealtToBuildings":10329,"damageDealtToObjectives":48966,"damageDealtToTurrets":10329,"damageSelfMitigated":44186,"deaths":10,"detectorWardsPlaced":3,"doubleKills":2,"dragonKills":1,"eligibleForProgression":true,"firstBloodAssist":false,"firstBloodKill":false,"firstTowerAssist":false,"firstTowerKill":true,"gameEndedInEarlySurrender":false,"gameEndedInSurrender":false,"goldEarned":20722,"goldSpent":17975,"individualPosition":"JUNGLE","inhibitorKills":1,"inhibitorTakedowns":1,"inhibitorsLost":2,"item0":3115,"item1":3157,"item2":3089,"item3":4633,"item4":3135,"item5":3158,"item6":3364,"itemsPurchased":24,"killingSprees":5,"kills":17,"lane":"JUNGLE","largestCriticalStrike":0,"largestKillingSpree":4,"largestMultiKill":2,"longestTimeSpentLiving":571,"magicDamageDealt":178691,"magicDamageDealtToChampions":32666,"magicDamageTaken":18933,"neutralMinionsKilled":168,"nexusKills":0,"nexusLost":1,"nexusTakedowns":0,"objectivesStolen":0,"objectivesStolenAssists":0,"participantId":2,"pentaKills":0,"perks":{"statPerks":{"defense":5002,"flex":5008,"offense":5005},"styles":[{"description":"primaryStyle","selections":[{"perk":8010,"var1":1449,"var2":0,"var3":0},{"perk":9111,"var1":2314,"var2":500,"var3":0},{"perk":9104,"var1":11,"var2":50,"var3":0},{"perk":8299,"var1":1685,"var2":0,"var3":0}],"style":8000},{"description":"subStyle","selections":[{"perk":8304,"var1":10,"var2":3,"var3":0},{"perk":8347,"var1":0,"var2":0,"var3":0}],"style":8300}]},"physicalDamageDealt":46800,"physicalDamageDealtToChampions":4815,"physicalDamageTaken":41043,"profileIcon":5499,"puuid":"YOqYLYrvcDcUwmtPr8pbdueWlKAmR7L5hf9whqVhWRiI1r-APuKmYs6fj4BXihErar7oM9bx8ohPMA","quadraKills":0,"riotIdName":"","riotIdTagline":"","role":"NONE","sightWardsBoughtInGame":0,"spell1Casts":146,"spell2Casts":33,"spell3Casts":182,"spell4Casts":45,"summoner1Casts":10,"summoner1Id":6,"summoner2Casts":26,"summoner2Id":11,"summonerId":"SVaIAgpYJkeLG2vvxyK2ZJx5MsNaYrLpakD6mXBqN1XEAqA","summonerLevel":711,"summonerName":"DIV Timon","teamEarlySurrendered":false,"teamId":100,"teamPosition":"JUNGLE","timeCCingOthers":19,"timePlayed":2188,"totalDamageDealt":293091,"totalDamageDealtToChampions":51820,"totalDamageShieldedOnTeammates":0,"totalDamageTaken":62486,"totalHeal":26191,"totalHealsOnTeammates":0,"totalMinionsKilled":75,"totalTimeCCDealt":268,"totalTimeSpentDead":385,"totalUnitsHealed":1,"tripleKills":0,"trueDamageDealt":67601,"trueDamageDealtToChampions":14338,"trueDamageTaken":2510,"turretKills":6,"turretTakedowns":7,"turretsLost":8,"unrealKills":0,"visionScore":33,"visionWardsBoughtInGame":3,"wardsKilled":4,"wardsPlaced":4,"win":false},{"assists":14,"baronKills":0,"basicPings":86,"bountyLevel":0,"challenges":{"12AssistStreakCount":0,"abilityUses":366,"acesBefore15Minutes":0,"alliedJungleMonsterKills":0,"baronTakedowns":0,"blastConeOppositeOpponentCount":0,"bountyGold":950,"buffsStolen":0,"completeSupportQuestInTime":0,"controlWardTimeCoverageInRiverOrEnemyHalf":0.15232346051516008,"controlWardsPlaced":2,"damagePerMinute":943.4550940914559,"damageTakenOnTeamPercentage":0.2759339571138559,"dancedWithRiftHerald":0,"deathsByEnemyChamps":11,"dodgeSkillShotsSmallWindow":21,"doubleAces":0,"dragonTakedowns":1,"earliestDragonTakedown":1859.0609152956542,"earliestElderDragon":1859.0609152956542,"earlyLaningPhaseGoldExpAdvantage":0,"effectiveHealAndShielding":0,"elderDragonKillsWithOpposingSoul":1,"elderDragonMultikills":0,"enemyChampionImmobilizations":147,"enemyJungleMonsterKills":0,"epicMonsterKillsNearEnemyJungler":0,"epicMonsterKillsWithin30SecondsOfSpawn":0,"epicMonsterSteals":0,"epicMonsterStolenWithoutSmite":0,"firstTurretKilledTime":671.7035906723263,"flawlessAces":0,"fullTeamTakedown":1,"gameLength":2188.924978844632,"getTakedownsInAllLanesEarlyJungleAsLaner":0,"goldPerMinute":430.08893015632776,"hadOpenNexus":0,"immobilizeAndKillWithAlly":19,"initialBuffCount":0,"initialCrabCount":0,"jungleCsBefore10Minutes":0,"junglerTakedownsNearDamagedEpicMonster":1,"kTurretsDestroyedBeforePlatesFall":0,"kda":2.3636363636363638,"killAfterHiddenWithAlly":3,"killParticipation":0.5306122448979592,"killedChampTookFullTeamDamageSurvived":0,"killingSprees":2,"killsNearEnemyTurret":1,"killsOnOtherLanesEarlyJungleAsLaner":1,"killsOnRecentlyHealedByAramPack":0,"killsUnderOwnTurret":2,"killsWithHelpFromEpicMonster":3,"knockEnemyIntoTeamAndKill":15,"landSkillShotsEarlyGame":2,"laneMinionsFirst10Minutes":63,"laningPhaseGoldExpAdvantage":0,"legendaryCount":0,"lostAnInhibitor":0,"maxCsAdvantageOnLaneOpponent":1,"maxKillDeficit":0,"maxLevelLeadLaneOpponent":0,"moreEnemyJungleThanOpponent":-143.25000008940697,"multiKillOneSpell":0,"multiTurretRiftHeraldCount":1,"multikills":2,"multikillsAfterAggressiveFlash":1,"mythicItemUsed":3068,"outerTurretExecutesBefore10Minutes":0,"outnumberedKills":3,"outnumberedNexusKill":0,"perfectDragonSoulsTaken":0,"perfectGame":0,"pickKillWithAlly":19,"playedChampSelectPosition":1,"poroExplosions":0,"quickCleanse":0,"quickFirstTurret":0,"quickSoloKills":0,"riftHeraldTakedowns":1,"saveAllyFromDeath":0,"scuttleCrabKills":2,"skillshotsDodged":113,"skillshotsHit":30,"snowballsHit":0,"soloBaronKills":0,"soloKills":1,"stealthWardsPlaced":6,"survivedSingleDigitHpCount":0,"survivedThreeImmobilizesInFight":8,"takedownOnFirstTurret":0,"takedowns":26,"takedownsAfterGainingLevelAdvantage":0,"takedownsBeforeJungleMinionSpawn":0,"takedownsFirstXMinutes":4,"takedownsInAlcove":0,"takedownsInEnemyFountain":0,"teamBaronKills":0,"teamDamagePercentage":0.2160539219900658,"teamElderDragonKills":1,"teamRiftHeraldKills":2,"threeWardsOneSweeperCount":0,"tookLargeDamageSurvived":0,"turretPlatesTaken":0,"turretTakedowns":1,"turretsTakenWithRiftHerald":15,"twentyMinionsIn3SecondsCount":6,"unseenRecalls":0,"visionScoreAdvantageLaneOpponent":0.5571906566619873,"visionScorePerMinute":0.9750640784574209,"wardTakedowns":8,"wardTakedownsBefore20M":1,"wardsGuarded":1},"champExperience":17813,"champLevel":17,"championId":154,"championName":"Zac","championTransform":0,"consumablesPurchased":5,"damageDealtToBuildings":159,"damageDealtToObjectives":10416,"damageDealtToTurrets":159,"damageSelfMitigated":78338,"deaths":11,"detectorWardsPlaced":2,"doubleKills":2,"dragonKills":0,"eligibleForProgression":true,"firstBloodAssist":false,"firstBloodKill":false,"firstTowerAssist":false,"firstTowerKill":false,"gameEndedInEarlySurrender":false,"gameEndedInSurrender":false,"goldEarned":15690,"goldSpent":15350,"individualPosition":"MIDDLE","inhibitorKills":0,"inhibitorTakedowns":0,"inhibitorsLost":2,"item0":3143,"item1":4637,"item2":1031,"item3":3075,"item4":3068,"item5":3158,"item6":3364,"itemsPurchased":27,"killingSprees":5,"kills":12,"lane":"MIDDLE","largestCriticalStrike":2,"largestKillingSpree":3,"largestMultiKill":2,"longestTimeSpentLiving":536,"magicDamageDealt":108987,"magicDamageDealtToChampions":29101,"magicDamageTaken":22240,"neutralMinionsKilled":8,"nexusKills":0,"nexusLost":1,"nexusTakedowns":0,"objectivesStolen":0,"objectivesStolenAssists":0,"participantId":3,"pentaKills":0,"perks":{"statPerks":{"defense":5001,"flex":5002,"offense":5007},"styles":[{"description":"primaryStyle","selections":[{"perk":8010,"var1":927,"var2":0,"var3":0},{"perk":9111,"var1":3739,"var2":520,"var3":0},{"perk":9105,"var1":16,"var2":10,"var3":0},{"perk":8299,"var1":1576,"var2":0,"var3":0}],"style":8000},{"description":"subStyle","selections":[{"perk":8444,"var1":3242,"var2":0,"var3":0},{"perk":8453,"var1":4520,"var2":277,"var3":0}],"style":8400}]},"physicalDamageDealt":12129,"physicalDamageDealtToChampions":1901,"physicalDamageTaken":38233,"profileIcon":4780,"puuid":"QWFRN5F1plRJavwMotH0klv3JEQFkXQ_WO_Ronhi6CY9XrPf_rIMJiMhSE5EL5cYR7Cfn8kQSkzyLA","quadraKills":0,"riotIdName":"","riotIdTagline":"","role":"SOLO","sightWardsBoughtInGame":0,"spell1Casts":64,"spell2Casts":189,"spell3Casts":99,"spell4Casts":14,"summoner1Casts":5,"summoner1Id":4,"summoner2Casts":5,"summoner2Id":12,"summonerId":"Iytxby44xywWM1gak-BiGUDSUap0o6O4KStKEmdFdDhRnc5X","summonerLevel":135,"summonerName":"BDM Account","teamEarlySurrendered":false,"teamId":100,"teamPosition":"MIDDLE","timeCCingOthers":62,"timePlayed":2188,"totalDamageDealt":134546,"totalDamageDealtToChampions":34419,"totalDamageShieldedOnTeammates":0,"totalDamageTaken":69266,"totalHeal":45483,"totalHealsOnTeammates":0,"totalMinionsKilled":151,"totalTimeCCDealt":364,"totalTimeSpentDead":418,"totalUnitsHealed":1,"tripleKills":0,"trueDamageDealt":13430,"trueDamageDealtToChampions":3416,"trueDamageTaken":8793,"turretKills":1,"turretTakedowns":1,"turretsLost":8,"unrealKills":0,"visionScore":35,"visionWardsBoughtInGame":2,"wardsKilled":8,"wardsPlaced":8,"win":false},{"assists":17,"baronKills":0,"basicPings":20,"bountyLevel":0,"challenges":{"12AssistStreakCount":0,"abilityUses":154,"acesBefore15Minutes":0,"alliedJungleMonsterKills":15.000000029802322,"baronTakedowns":0,"blastConeOppositeOpponentCount":0,"bountyGold":0,"buffsStolen":0,"completeSupportQuestInTime":0,"controlWardTimeCoverageInRiverOrEnemyHalf":0.05033520446807013,"controlWardsPlaced":3,"damagePerMinute":1041.9242351461521,"damageTakenOnTeamPercentage":0.13110988686479508,"dancedWithRiftHerald":0,"deathsByEnemyChamps":12,"dodgeSkillShotsSmallWindow":11,"doubleAces":0,"dragonTakedowns":1,"earliestDragonTakedown":1859.0609152956542,"earliestElderDragon":1859.0609152956542,"earlyLaningPhaseGoldExpAdvantage":0,"effectiveHealAndShielding":1177.4764404296875,"elderDragonKillsWithOpposingSoul":1,"elderDragonMultikills":0,"enemyChampionImmobilizations":26,"enemyJungleMonsterKills":0,"epicMonsterKillsNearEnemyJungler":0,"epicMonsterKillsWithin30SecondsOfSpawn":0,"epicMonsterSteals":0,"epicMonsterStolenWithoutSmite":0,"firstTurretKilledTime":671.7035906723263,"flawlessAces":0,"fullTeamTakedown":1,"gameLength":2188.924978844632,"getTakedownsInAllLanesEarlyJungleAsLaner":0,"goldPerMinute":426.9181474498261,"hadOpenNexus":0,"immobilizeAndKillWithAlly":3,"initialBuffCount":0,"initialCrabCount":0,"jungleCsBefore10Minutes":0,"junglerTakedownsNearDamagedEpicMonster":0,"kTurretsDestroyedBeforePlatesFall":1,"kda":2,"killAfterHiddenWithAlly":5,"killParticipation":0.4897959183673469,"killedChampTookFullTeamDamageSurvived":0,"killsNearEnemyTurret":3,"killsOnOtherLanesEarlyJungleAsLaner":0,"killsOnRecentlyHealedByAramPack":0,"killsUnderOwnTurret":0,"killsWithHelpFromEpicMonster":1,"knockEnemyIntoTeamAndKill":0,"landSkillShotsEarlyGame":20,"laneMinionsFirst10Minutes":52,"laningPhaseGoldExpAdvantage":0,"legendaryCount":0,"lostAnInhibitor":0,"maxCsAdvantageOnLaneOpponent":23,"maxKillDeficit":0,"maxLevelLeadLaneOpponent":2,"moreEnemyJungleThanOpponent":-143.25000008940697,"multiKillOneSpell":0,"multiTurretRiftHeraldCount":1,"multikills":1,"multikillsAfterAggressiveFlash":0,"mythicItemUsed":6673,"outerTurretExecutesBefore10Minutes":0,"outnumberedKills":3,"outnumberedNexusKill":0,"perfectDragonSoulsTaken":0,"perfectGame":0,"pickKillWithAlly":20,"playedChampSelectPosition":1,"poroExplosions":0,"quickCleanse":0,"quickFirstTurret":0,"quickSoloKills":0,"riftHeraldTakedowns":0,"saveAllyFromDeath":2,"scuttleCrabKills":0,"skillshotsDodged":59,"skillshotsHit":92,"snowballsHit":0,"soloBaronKills":0,"soloKills":0,"stealthWardsPlaced":5,"survivedSingleDigitHpCount":0,"survivedThreeImmobilizesInFight":0,"takedownOnFirstTurret":0,"takedowns":24,"takedownsAfterGainingLevelAdvantage":0,"takedownsBeforeJungleMinionSpawn":0,"takedownsFirstXMinutes":7,"takedownsInAlcove":0,"takedownsInEnemyFountain":0,"teamBaronKills":0,"teamDamagePercentage":0.2386036376607915,"teamElderDragonKills":1,"teamRiftHeraldKills":2,"threeWardsOneSweeperCount":0,"tookLargeDamageSurvived":0,"turretPlatesTaken":7,"turretTakedowns":3,"turretsTakenWithRiftHerald":15,"twentyMinionsIn3SecondsCount":9,"unseenRecalls":0,"visionScoreAdvantageLaneOpponent":0.020398497581481934,"visionScorePerMinute":0.6804607877162735,"wardTakedowns":4,"wardTakedownsBefore20M":2,"wardsGuarded":0},"champExperience":17114,"champLevel":17,"championId":110,"championName":"Varus","championTransform":0,"consumablesPurchased":8,"damageDealtToBuildings":3749,"damageDealtToObjectives":9693,"damageDealtToTurrets":3749,"damageSelfMitigated":26631,"deaths":12,"detectorWardsPlaced":3,"doubleKills":1,"dragonKills":0,"eligibleForProgression":true,"firstBloodAssist":false,"firstBloodKill":false,"firstTowerAssist":true,"firstTowerKill":false,"gameEndedInEarlySurrender":false,"gameEndedInSurrender":false,"goldEarned":15574,"goldSpent":15550,"individualPosition":"BOTTOM","inhibitorKills":0,"inhibitorTakedowns":1,"inhibitorsLost":2,"item0":3091,"item1":3072,"item2":1038,"item3":3006,"item4":6673,"item5":3124,"item6":3363,"itemsPurchased":29,"killingSprees":1,"kills":7,"lane":"BOTTOM","largestCriticalStrike":266,"largestKillingSpree":2,"largestMultiKill":2,"longestTimeSpentLiving":405,"magicDamageDealt":29299,"magicDamageDealtToChampions":8990,"magicDamageTaken":7213,"neutralMinionsKilled":15,"nexusKills":0,"nexusLost":1,"nexusTakedowns":0,"objectivesStolen":0,"objectivesStolenAssists":0,"participantId":4,"pentaKills":0,"perks":{"statPerks":{"defense":5002,"flex":5008,"offense":5005},"styles":[{"description":"primaryStyle","selections":[{"perk":8008,"var1":90,"var2":6,"var3":0},{"perk":8009,"var1":3578,"var2":0,"var3":0},{"perk":9104,"var1":11,"var2":50,"var3":0},{"perk":8017,"var1":1535,"var2":0,"var3":0}],"style":8000},{"description":"subStyle","selections":[{"perk":8345,"var1":3,"var2":0,"var3":0},{"perk":8347,"var1":0,"var2":0,"var3":0}],"style":8300}]},"physicalDamageDealt":157788,"physicalDamageDealtToChampions":26438,"physicalDamageTaken":23971,"profileIcon":5034,"puuid":"uGEzT6chd6zFfSEYVmiv6d-zEPgFlrwzRHpZlWzNk9BvMf_NCVtu2u_Msxtj_lggVlpRdDQTw07GYg","quadraKills":0,"riotIdName":"","riotIdTagline":"","role":"CARRY","sightWardsBoughtInGame":0,"spell1Casts":57,"spell2Casts":25,"spell3Casts":58,"spell4Casts":14,"summoner1Casts":7,"summoner1Id":7,"summoner2Casts":5,"summoner2Id":4,"summonerId":"ODekZlmOsK40HWWqXHSxTp_ClwWGJ-sk9jd-UirGoeWPLAknFRV4pSJ84Q","summonerLevel":529,"summonerName":"dont drop dead","teamEarlySurrendered":false,"teamId":100,"teamPosition":"BOTTOM","timeCCingOthers":38,"timePlayed":2188,"totalDamageDealt":192662,"totalDamageDealtToChampions":38011,"totalDamageShieldedOnTeammates":0,"totalDamageTaken":32911,"totalHeal":2175,"totalHealsOnTeammates":1177,"totalMinionsKilled":222,"totalTimeCCDealt":371,"totalTimeSpentDead":408,"totalUnitsHealed":4,"tripleKills":0,"trueDamageDealt":5574,"trueDamageDealtToChampions":2582,"trueDamageTaken":1727,"turretKills":0,"turretTakedowns":3,"turretsLost":8,"unrealKills":0,"visionScore":24,"visionWardsBoughtInGame":4,"wardsKilled":4,"wardsPlaced":14,"win":false},{"assists":30,"baronKills":0,"basicPings":116,"bountyLevel":0,"challenges":{"12AssistStreakCount":1,"abilityUses":273,"acesBefore15Minutes":0,"alliedJungleMonsterKills":0,"baronTakedowns":0,"blastConeOppositeOpponentCount":0,"bountyGold":0,"buffsStolen":0,"completeSupportQuestInTime":1,"controlWardTimeCoverageInRiverOrEnemyHalf":0.38252697657556567,"controlWardsPlaced":14,"damagePerMinute":254.53673460308983,"damageTakenOnTeamPercentage":0.14834653532197783,"dancedWithRiftHerald":0,"deathsByEnemyChamps":8,"dodgeSkillShotsSmallWindow":15,"doubleAces":0,"dragonTakedowns":1,"earliestDragonTakedown":1859.0609152956542,"earliestElderDragon":1859.0609152956542,"earlyLaningPhaseGoldExpAdvantage":0,"effectiveHealAndShielding":13743.513671875,"elderDragonKillsWithOpposingSoul":1,"elderDragonMultikills":0,"enemyChampionImmobilizations":36,"enemyJungleMonsterKills":0,"epicMonsterKillsNearEnemyJungler":0,"epicMonsterKillsWithin30SecondsOfSpawn":0,"epicMonsterSteals":0,"epicMonsterStolenWithoutSmite":0,"firstTurretKilledTime":671.7035906723263,"flawlessAces":0,"fullTeamTakedown":1,"gameLength":2188.924978844632,"getTakedownsInAllLanesEarlyJungleAsLaner":0,"goldPerMinute":324.07370476359335,"hadOpenNexus":0,"immobilizeAndKillWithAlly":12,"initialBuffCount":0,"initialCrabCount":0,"jungleCsBefore10Minutes":0,"junglerTakedownsNearDamagedEpicMonster":0,"kTurretsDestroyedBeforePlatesFall":0,"kda":4.25,"killAfterHiddenWithAlly":4,"killParticipation":0.6938775510204082,"killedChampTookFullTeamDamageSurvived":0,"killsNearEnemyTurret":1,"killsOnOtherLanesEarlyJungleAsLaner":0,"killsOnRecentlyHealedByAramPack":0,"killsUnderOwnTurret":1,"killsWithHelpFromEpicMonster":1,"knockEnemyIntoTeamAndKill":0,"landSkillShotsEarlyGame":5,"laneMinionsFirst10Minutes":17,"laningPhaseGoldExpAdvantage":0,"legendaryCount":0,"lostAnInhibitor":0,"maxCsAdvantageOnLaneOpponent":13,"maxKillDeficit":0,"maxLevelLeadLaneOpponent":1,"moreEnemyJungleThanOpponent":-143.25000008940697,"multiKillOneSpell":0,"multiTurretRiftHeraldCount":1,"multikills":0,"multikillsAfterAggressiveFlash":0,"mythicItemUsed":2065,"outerTurretExecutesBefore10Minutes":0,"outnumberedKills":0,"outnumberedNexusKill":0,"perfectDragonSoulsTaken":0,"perfectGame":0,"pickKillWithAlly":25,"playedChampSelectPosition":1,"poroExplosions":0,"quickCleanse":0,"quickFirstTurret":0,"quickSoloKills":0,"riftHeraldTakedowns":0,"saveAllyFromDeath":13,"scuttleCrabKills":0,"skillshotsDodged":82,"skillshotsHit":32,"snowballsHit":0,"soloBaronKills":0,"soloKills":0,"stealthWardsPlaced":35,"survivedSingleDigitHpCount":0,"survivedThreeImmobilizesInFight":4,"takedownOnFirstTurret":0,"takedowns":34,"takedownsAfterGainingLevelAdvantage":0,"takedownsBeforeJungleMinionSpawn":0,"takedownsFirstXMinutes":9,"takedownsInAlcove":0,"takedownsInEnemyFountain":0,"teamBaronKills":0,"teamDamagePercentage":0.058289642131299065,"teamElderDragonKills":1,"teamRiftHeraldKills":2,"threeWardsOneSweeperCount":0,"tookLargeDamageSurvived":0,"turretPlatesTaken":2,"turretTakedowns":3,"turretsTakenWithRiftHerald":15,"twentyMinionsIn3SecondsCount":1,"unseenRecalls":0,"visionScoreAdvantageLaneOpponent":0.4367746114730835,"visionScorePerMinute":2.577532023932145,"wardTakedowns":5,"wardTakedownsBefore20M":5,"wardsGuarded":0},"champExperience":15984,"champLevel":16,"championId":497,"championName":"Rakan","championTransform":0,"consumablesPurchased":21,"damageDealtToBuildings":130,"damageDealtToObjectives":1430,"damageDealtToTurrets":130,"damageSelfMitigated":33588,"deaths":8,"detectorWardsPlaced":14,"doubleKills":0,"dragonKills":0,"eligibleForProgression":true,"firstBloodAssist":false,"firstBloodKill":false,"firstTowerAssist":false,"firstTowerKill":false,"gameEndedInEarlySurrender":false,"gameEndedInSurrender":false,"goldEarned":11822,"goldSpent":10925,"individualPosition":"UTILITY","inhibitorKills":0,"inhibitorTakedowns":1,"inhibitorsLost":2,"item0":3860,"item1":2065,"item2":4643,"item3":3158,"item4":3067,"item5":3011,"item6":3364,"itemsPurchased":38,"killingSprees":1,"kills":4,"lane":"BOTTOM","largestCriticalStrike":0,"largestKillingSpree":2,"largestMultiKill":1,"longestTimeSpentLiving":804,"magicDamageDealt":17277,"magicDamageDealtToChampions":6478,"magicDamageTaken":9944,"neutralMinionsKilled":0,"nexusKills":0,"nexusLost":1,"nexusTakedowns":0,"objectivesStolen":0,"objectivesStolenAssists":0,"participantId":5,"pentaKills":0,"perks":{"statPerks":{"defense":5002,"flex":5002,"offense":5008},"styles":[{"description":"primaryStyle","selections":[{"perk":8465,"var1":5441,"var2":0,"var3":0},{"perk":8463,"var1":935,"var2":0,"var3":0},{"perk":8444,"var1":1865,"var2":0,"var3":0},{"perk":8242,"var1":147,"var2":0,"var3":0}],"style":8400},{"description":"subStyle","selections":[{"perk":8316,"var1":884,"var2":0,"var3":0},{"perk":8347,"var1":0,"var2":0,"var3":0}],"style":8300}]},"physicalDamageDealt":6315,"physicalDamageDealtToChampions":1546,"physicalDamageTaken":25612,"profileIcon":5516,"puuid":"_Xsx3gnqgOXgqr583lUsxGdp51yJn4J4vmlHIZHq_gBVBOwHJcf-sP7t40Yk1faH4uxfC7Bt2vo42Q","quadraKills":0,"riotIdName":"","riotIdTagline":"","role":"SUPPORT","sightWardsBoughtInGame":0,"spell1Casts":52,"spell2Casts":71,"spell3Casts":136,"spell4Casts":14,"summoner1Casts":6,"summoner1Id":4,"summoner2Casts":8,"summoner2Id":14,"summonerId":"Q2gjtSXc9pm4NYGTF-W9ig8cNot66aRfLe0F1UAIJOYQP60","summonerLevel":454,"summonerName":"the hours pass","teamEarlySurrendered":false,"teamId":100,"teamPosition":"UTILITY","timeCCingOthers":35,"timePlayed":2188,"totalDamageDealt":33221,"totalDamageDealtToChampions":9286,"totalDamageShieldedOnTeammates":9950,"totalDamageTaken":37238,"totalHeal":10193,"totalHealsOnTeammates":3793,"totalMinionsKilled":38,"totalTimeCCDealt":79,"totalTimeSpentDead":225,"totalUnitsHealed":5,"tripleKills":0,"trueDamageDealt":9628,"trueDamageDealtToChampions":1260,"trueDamageTaken":1682,"turretKills":0,"turretTakedowns":3,"turretsLost":8,"unrealKills":0,"visionScore":94,"visionWardsBoughtInGame":8,"wardsKilled":5,"wardsPlaced":50,"win":false},{"assists":17,"baronKills":0,"basicPings":59,"bountyLevel":1,"challenges":{"12AssistStreakCount":0,"abilityUses":241,"acesBefore15Minutes":0,"alliedJungleMonsterKills":2.0000000298023224,"baronBuffGoldAdvantageOverThreshold":1,"baronTakedowns":1,"blastConeOppositeOpponentCount":0,"bountyGold":150,"buffsStolen":0,"completeSupportQuestInTime":0,"controlWardTimeCoverageInRiverOrEnemyHalf":0.10586939231647594,"controlWardsPlaced":3,"damagePerMinute":699.727684161402,"damageTakenOnTeamPercentage":0.212944972373369,"dancedWithRiftHerald":0,"deathsByEnemyChamps":9,"dodgeSkillShotsSmallWindow":18,"doubleAces":0,"dragonTakedowns":2,"earliestBaron":1723.2915894011035,"earliestDragonTakedown":1071.3877986176212,"earlyLaningPhaseGoldExpAdvantage":1,"effectiveHealAndShielding":87.3623046875,"elderDragonKillsWithOpposingSoul":0,"elderDragonMultikills":0,"enemyChampionImmobilizations":63,"enemyJungleMonsterKills":0,"epicMonsterKillsNearEnemyJungler":0,"epicMonsterKillsWithin30SecondsOfSpawn":0,"epicMonsterSteals":0,"epicMonsterStolenWithoutSmite":0,"flawlessAces":2,"fullTeamTakedown":1,"gameLength":2188.924978844632,"getTakedownsInAllLanesEarlyJungleAsLaner":0,"goldPerMinute":354.8040614284457,"hadOpenNexus":0,"immobilizeAndKillWithAlly":7,"initialBuffCount":0,"initialCrabCount":0,"jungleCsBefore10Minutes":0,"junglerTakedownsNearDamagedEpicMonster":0,"kTurretsDestroyedBeforePlatesFall":0,"kda":2.5555555555555554,"killAfterHiddenWithAlly":2,"killParticipation":0.4423076923076923,"killedChampTookFullTeamDamageSurvived":0,"killsNearEnemyTurret":1,"killsOnOtherLanesEarlyJungleAsLaner":0,"killsOnRecentlyHealedByAramPack":0,"killsUnderOwnTurret":3,"killsWithHelpFromEpicMonster":1,"knockEnemyIntoTeamAndKill":5,"landSkillShotsEarlyGame":7,"laneMinionsFirst10Minutes":64,"laningPhaseGoldExpAdvantage":1,"legendaryCount":0,"lostAnInhibitor":1,"maxCsAdvantageOnLaneOpponent":16,"maxKillDeficit":3,"maxLevelLeadLaneOpponent":2,"moreEnemyJungleThanOpponent":-119.40000006556511,"multiKillOneSpell":0,"multiTurretRiftHeraldCount":0,"multikills":0,"multikillsAfterAggressiveFlash":0,"mythicItemUsed":7004,"outerTurretExecutesBefore10Minutes":0,"outnumberedKills":2,"outnumberedNexusKill":0,"perfectDragonSoulsTaken":1,"perfectGame":0,"pickKillWithAlly":14,"playedChampSelectPosition":1,"poroExplosions":0,"quickCleanse":0,"quickFirstTurret":0,"quickSoloKills":0,"riftHeraldTakedowns":0,"saveAllyFromDeath":0,"scuttleCrabKills":0,"shortestTimeToAceFromFirstTakedown":39.097569014399596,"skillshotsDodged":91,"skillshotsHit":48,"snowballsHit":0,"soloBaronKills":0,"soloKills":2,"stealthWardsPlaced":8,"survivedSingleDigitHpCount":0,"survivedThreeImmobilizesInFight":6,"takedownOnFirstTurret":0,"takedowns":23,"takedownsAfterGainingLevelAdvantage":0,"takedownsBeforeJungleMinionSpawn":0,"takedownsFirstXMinutes":3,"takedownsInAlcove":0,"takedownsInEnemyFountain":0,"teamBaronKills":2,"teamDamagePercentage":0.1246920726137027,"teamElderDragonKills":0,"teamRiftHeraldKills":0,"threeWardsOneSweeperCount":0,"tookLargeDamageSurvived":2,"turretPlatesTaken":3,"turretTakedowns":2,"turretsTakenWithRiftHerald":0,"twentyMinionsIn3SecondsCount":7,"unseenRecalls":0,"visionScoreAdvantageLaneOpponent":-0.08902114629745483,"visionScorePerMinute":0.654245129321549,"wardTakedowns":2,"wardTakedownsBefore20M":1,"wardsGuarded":1},"champExperience":18154,"champLevel":17,"championId":516,"championName":"Ornn","championTransform":0,"consumablesPurchased":8,"damageDealtToBuildings":1255,"damageDealtToObjectives":6523,"damageDealtToTurrets":1255,"damageSelfMitigated":59013,"deaths":9,"detectorWardsPlaced":3,"doubleKills":0,"dragonKills":0,"eligibleForProgression":true,"firstBloodAssist":false,"firstBloodKill":true,"firstTowerAssist":false,"firstTowerKill":false,"gameEndedInEarlySurrender":false,"gameEndedInSurrender":false,"goldEarned":12943,"goldSpent":12850,"individualPosition":"TOP","inhibitorKills":0,"inhibitorTakedowns":1,"inhibitorsLost":1,"item0":1028,"item1":3082,"item2":3075,"item3":4401,"item4":3111,"item5":7004,"item6":3364,"itemsPurchased":35,"killingSprees":2,"kills":6,"lane":"TOP","largestCriticalStrike":0,"largestKillingSpree":2,"largestMultiKill":1,"longestTimeSpentLiving":527,"magicDamageDealt":71011,"magicDamageDealtToChampions":17063,"magicDamageTaken":11624,"neutralMinionsKilled":2,"nexusKills":0,"nexusLost":0,"nexusTakedowns":0,"objectivesStolen":0,"objectivesStolenAssists":0,"participantId":6,"pentaKills":0,"perks":{"statPerks":{"defense":5002,"flex":5003,"offense":5008},"styles":[{"description":"primaryStyle","selections":[{"perk":8360,"var1":16,"var2":0,"var3":0},{"perk":8304,"var1":9,"var2":4,"var3":5},{"perk":8345,"var1":3,"var2":0,"var3":0},{"perk":8347,"var1":0,"var2":0,"var3":0}],"style":8300},{"description":"subStyle","selections":[{"perk":8242,"var1":124,"var2":0,"var3":0},{"perk":8429,"var1":67,"var2":18,"var3":16}],"style":8400}]},"physicalDamageDealt":49303,"physicalDamageDealtToChampions":6715,"physicalDamageTaken":22189,"profileIcon":5544,"puuid":"qhQcyLEC26FRmtUCKdc24ErrxadSAz-tasWjqoNXaLSWPKy0lCV9zJLlejDVeqkZHdFSpnG-Gzoabg","quadraKills":0,"riotIdName":"","riotIdTagline":"","role":"DUO","sightWardsBoughtInGame":0,"spell1Casts":89,"spell2Casts":74,"spell3Casts":51,"spell4Casts":27,"summoner1Casts":9,"summoner1Id":4,"summoner2Casts":13,"summoner2Id":12,"summonerId":"qRaZbaQ7FlAG2gdzjU_ziU7eaFcMCByTssur4Fp9J5jtK3E","summonerLevel":643,"summonerName":"UNLEASHED MANGO","teamEarlySurrendered":false,"teamId":200,"teamPosition":"TOP","timeCCingOthers":50,"timePlayed":2188,"totalDamageDealt":127997,"totalDamageDealtToChampions":25527,"totalDamageShieldedOnTeammates":0,"totalDamageTaken":42124,"totalHeal":6304,"totalHealsOnTeammates":87,"totalMinionsKilled":159,"totalTimeCCDealt":571,"totalTimeSpentDead":346,"totalUnitsHealed":2,"tripleKills":0,"trueDamageDealt":7682,"trueDamageDealtToChampions":1748,"trueDamageTaken":8310,"turretKills":0,"turretTakedowns":2,"turretsLost":8,"unrealKills":0,"visionScore":23,"visionWardsBoughtInGame":4,"wardsKilled":2,"wardsPlaced":11,"win":true},{"assists":14,"baronKills":2,"basicPings":95,"bountyLevel":3,"challenges":{"12AssistStreakCount":0,"abilityUses":310,"acesBefore15Minutes":0,"alliedJungleMonsterKills":114.40000015497208,"baronBuffGoldAdvantageOverThreshold":1,"baronTakedowns":2,"blastConeOppositeOpponentCount":0,"bountyGold":1125,"buffsStolen":0,"completeSupportQuestInTime":0,"controlWardTimeCoverageInRiverOrEnemyHalf":0.09529572146484262,"controlWardsPlaced":3,"damagePerMinute":1773.2174997489951,"damageTakenOnTeamPercentage":0.24286163480190617,"dancedWithRiftHerald":0,"deathsByEnemyChamps":7,"dodgeSkillShotsSmallWindow":15,"doubleAces":0,"dragonTakedowns":3,"earliestBaron":1723.2915894011035,"earliestDragonTakedown":413.1778313029502,"earlyLaningPhaseGoldExpAdvantage":0,"effectiveHealAndShielding":0,"elderDragonKillsWithOpposingSoul":0,"elderDragonMultikills":0,"enemyChampionImmobilizations":0,"enemyJungleMonsterKills":12.500000029802322,"epicMonsterKillsNearEnemyJungler":0,"epicMonsterKillsWithin30SecondsOfSpawn":2,"epicMonsterSteals":0,"epicMonsterStolenWithoutSmite":0,"flawlessAces":2,"fullTeamTakedown":1,"gameLength":2188.924978844632,"goldPerMinute":581.1531044551585,"hadOpenNexus":0,"highestChampionDamage":1,"highestCrowdControlScore":1,"highestWardKills":1,"immobilizeAndKillWithAlly":0,"initialBuffCount":2,"initialCrabCount":2,"jungleCsBefore10Minutes":80.00000008940697,"junglerKillsEarlyJungle":0,"junglerTakedownsNearDamagedEpicMonster":1,"kTurretsDestroyedBeforePlatesFall":0,"kda":4.857142857142857,"killAfterHiddenWithAlly":5,"killParticipation":0.6538461538461539,"killedChampTookFullTeamDamageSurvived":0,"killingSprees":3,"killsNearEnemyTurret":3,"killsOnLanersEarlyJungleAsJungler":3,"killsOnRecentlyHealedByAramPack":0,"killsUnderOwnTurret":3,"killsWithHelpFromEpicMonster":1,"knockEnemyIntoTeamAndKill":0,"landSkillShotsEarlyGame":4,"laneMinionsFirst10Minutes":4,"laningPhaseGoldExpAdvantage":0,"legendaryCount":0,"lostAnInhibitor":1,"maxCsAdvantageOnLaneOpponent":20.25,"maxKillDeficit":3,"maxLevelLeadLaneOpponent":1,"moreEnemyJungleThanOpponent":-39.39999997615814,"multiKillOneSpell":0,"multiTurretRiftHeraldCount":0,"multikills":3,"multikillsAfterAggressiveFlash":1,"mythicItemUsed":7001,"outerTurretExecutesBefore10Minutes":0,"outnumberedKills":5,"outnumberedNexusKill":0,"perfectDragonSoulsTaken":1,"perfectGame":0,"pickKillWithAlly":17,"playedChampSelectPosition":1,"poroExplosions":0,"quickCleanse":0,"quickFirstTurret":0,"quickSoloKills":0,"riftHeraldTakedowns":0,"saveAllyFromDeath":0,"scuttleCrabKills":5,"shortestTimeToAceFromFirstTakedown":36.63611892320114,"skillshotsDodged":79,"skillshotsHit":82,"snowballsHit":0,"soloBaronKills":0,"soloKills":2,"stealthWardsPlaced":1,"survivedSingleDigitHpCount":0,"survivedThreeImmobilizesInFight":5,"takedownOnFirstTurret":0,"takedowns":34,"takedownsAfterGainingLevelAdvantage":0,"takedownsBeforeJungleMinionSpawn":0,"takedownsFirstXMinutes":5,"takedownsInAlcove":0,"takedownsInEnemyFountain":0,"teamBaronKills":2,"teamDamagePercentage":0.31598887716380364,"teamElderDragonKills":0,"teamRiftHeraldKills":0,"threeWardsOneSweeperCount":1,"tookLargeDamageSurvived":0,"turretPlatesTaken":2,"turretTakedowns":3,"turretsTakenWithRiftHerald":0,"twentyMinionsIn3SecondsCount":3,"unseenRecalls":0,"visionScoreAdvantageLaneOpponent":0.620284914970398,"visionScorePerMinute":1.5061696966214244,"wardTakedowns":13,"wardTakedownsBefore20M":6,"wardsGuarded":0},"champExperience":22354,"champLevel":18,"championId":104,"championName":"Graves","championTransform":0,"consumablesPurchased":7,"damageDealtToBuildings":5033,"damageDealtToObjectives":48306,"damageDealtToTurrets":5033,"damageSelfMitigated":49486,"deaths":7,"detectorWardsPlaced":3,"doubleKills":3,"dragonKills":2,"eligibleForProgression":true,"firstBloodAssist":false,"firstBloodKill":false,"firstTowerAssist":false,"firstTowerKill":false,"gameEndedInEarlySurrender":false,"gameEndedInSurrender":false,"goldEarned":21201,"goldSpent":18425,"individualPosition":"JUNGLE","inhibitorKills":0,"inhibitorTakedowns":1,"inhibitorsLost":1,"item0":7001,"item1":3156,"item2":3179,"item3":3111,"item4":6694,"item5":3071,"item6":3364,"itemsPurchased":34,"killingSprees":6,"kills":20,"lane":"JUNGLE","largestCriticalStrike":0,"largestKillingSpree":6,"largestMultiKill":2,"longestTimeSpentLiving":977,"magicDamageDealt":11295,"magicDamageDealtToChampions":1426,"magicDamageTaken":17648,"neutralMinionsKilled":175,"nexusKills":1,"nexusLost":0,"nexusTakedowns":1,"objectivesStolen":0,"objectivesStolenAssists":0,"participantId":7,"pentaKills":0,"perks":{"statPerks":{"defense":5003,"flex":5008,"offense":5005},"styles":[{"description":"primaryStyle","selections":[{"perk":8021,"var1":5563,"var2":4551,"var3":0},{"perk":9111,"var1":2205,"var2":680,"var3":0},{"perk":9104,"var1":10,"var2":30,"var3":0},{"perk":8299,"var1":1630,"var2":0,"var3":0}],"style":8000},{"description":"subStyle","selections":[{"perk":8136,"var1":13,"var2":30,"var3":0},{"perk":8135,"var1":550,"var2":5,"var3":0}],"style":8100}]},"physicalDamageDealt":268001,"physicalDamageDealtToChampions":55969,"physicalDamageTaken":22280,"profileIcon":26,"puuid":"D3-txI8fd4LnzH-6e36fZjRsz4_2PPgW9VThsvPTMwvRu5oQE7DBXm991TkegKqcGkmqjoAFkRS_QQ","quadraKills":0,"riotIdName":"","riotIdTagline":"","role":"NONE","sightWardsBoughtInGame":0,"spell1Casts":164,"spell2Casts":40,"spell3Casts":86,"spell4Casts":20,"summoner1Casts":20,"summoner1Id":11,"summoner2Casts":6,"summoner2Id":4,"summonerId":"1pBeQildRNAwjmilFi_fT2TOwVGO3sHbsoXTkU3L4Xg9O7yK","summonerLevel":106,"summonerName":"1Strike","teamEarlySurrendered":false,"teamId":200,"teamPosition":"JUNGLE","timeCCingOthers":37,"timePlayed":2188,"totalDamageDealt":300157,"totalDamageDealtToChampions":64690,"totalDamageShieldedOnTeammates":0,"totalDamageTaken":48042,"totalHeal":22955,"totalHealsOnTeammates":0,"totalMinionsKilled":82,"totalTimeCCDealt":663,"totalTimeSpentDead":330,"totalUnitsHealed":1,"tripleKills":0,"trueDamageDealt":20860,"trueDamageDealtToChampions":7294,"trueDamageTaken":8113,"turretKills":2,"turretTakedowns":3,"turretsLost":8,"unrealKills":0,"visionScore":54,"visionWardsBoughtInGame":3,"wardsKilled":13,"wardsPlaced":17,"win":true},{"assists":13,"baronKills":0,"basicPings":113,"bountyLevel":1,"challenges":{"12AssistStreakCount":0,"abilityUses":331,"acesBefore15Minutes":0,"alliedJungleMonsterKills":5.500000029802322,"baronBuffGoldAdvantageOverThreshold":1,"baronTakedowns":1,"blastConeOppositeOpponentCount":0,"bountyGold":0,"buffsStolen":0,"completeSupportQuestInTime":0,"controlWardTimeCoverageInRiverOrEnemyHalf":0.08708340718471975,"controlWardsPlaced":2,"damagePerMinute":1311.1508915279783,"damageTakenOnTeamPercentage":0.15110270995528177,"dancedWithRiftHerald":0,"deathsByEnemyChamps":9,"dodgeSkillShotsSmallWindow":17,"doubleAces":0,"dragonTakedowns":1,"earliestBaron":1723.2915894011035,"earliestDragonTakedown":1481.5410763881762,"earlyLaningPhaseGoldExpAdvantage":1,"effectiveHealAndShielding":0,"elderDragonKillsWithOpposingSoul":0,"elderDragonMultikills":0,"enemyChampionImmobilizations":42,"enemyJungleMonsterKills":2.0000000298023224,"epicMonsterKillsNearEnemyJungler":0,"epicMonsterKillsWithin30SecondsOfSpawn":0,"epicMonsterSteals":0,"epicMonsterStolenWithoutSmite":0,"flawlessAces":2,"fullTeamTakedown":1,"gameLength":2188.924978844632,"getTakedownsInAllLanesEarlyJungleAsLaner":0,"goldPerMinute":428.07076268590504,"hadOpenNexus":0,"immobilizeAndKillWithAlly":16,"initialBuffCount":0,"initialCrabCount":0,"jungleCsBefore10Minutes":0,"junglerTakedownsNearDamagedEpicMonster":0,"kTurretsDestroyedBeforePlatesFall":0,"kda":2.4444444444444446,"killAfterHiddenWithAlly":3,"killParticipation":0.4230769230769231,"killedChampTookFullTeamDamageSurvived":0,"killingSprees":1,"killsNearEnemyTurret":4,"killsOnOtherLanesEarlyJungleAsLaner":2,"killsOnRecentlyHealedByAramPack":0,"killsUnderOwnTurret":1,"killsWithHelpFromEpicMonster":3,"knockEnemyIntoTeamAndKill":0,"landSkillShotsEarlyGame":13,"laneMinionsFirst10Minutes":90,"laningPhaseGoldExpAdvantage":0,"legendaryCount":0,"lostAnInhibitor":1,"maxCsAdvantageOnLaneOpponent":136.75000005960464,"maxKillDeficit":3,"maxLevelLeadLaneOpponent":2,"moreEnemyJungleThanOpponent":-119.40000006556511,"multiKillOneSpell":0,"multiTurretRiftHeraldCount":0,"multikills":2,"multikillsAfterAggressiveFlash":1,"mythicItemUsed":7012,"outerTurretExecutesBefore10Minutes":0,"outnumberedKills":1,"outnumberedNexusKill":0,"perfectDragonSoulsTaken":1,"perfectGame":0,"pickKillWithAlly":14,"playedChampSelectPosition":1,"poroExplosions":0,"quickCleanse":0,"quickFirstTurret":0,"quickSoloKills":0,"riftHeraldTakedowns":0,"saveAllyFromDeath":0,"scuttleCrabKills":1,"shortestTimeToAceFromFirstTakedown":42.60274134036467,"skillshotsDodged":90,"skillshotsHit":75,"snowballsHit":0,"soloBaronKills":0,"soloKills":2,"stealthWardsPlaced":2,"survivedSingleDigitHpCount":0,"survivedThreeImmobilizesInFight":4,"takedownOnFirstTurret":0,"takedowns":22,"takedownsAfterGainingLevelAdvantage":0,"takedownsBeforeJungleMinionSpawn":0,"takedownsFirstXMinutes":5,"takedownsInAlcove":0,"takedownsInEnemyFountain":0,"teamBaronKills":2,"teamDamagePercentage":0.23364821183238538,"teamElderDragonKills":0,"teamRiftHeraldKills":0,"threeWardsOneSweeperCount":0,"tookLargeDamageSurvived":0,"turretPlatesTaken":1,"turretTakedowns":1,"turretsTakenWithRiftHerald":0,"twentyMinionsIn3SecondsCount":13,"unseenRecalls":0,"visionScoreAdvantageLaneOpponent":-0.3578178882598877,"visionScorePerMinute":0.6261687097080569,"wardTakedowns":4,"wardTakedownsBefore20M":3,"wardsGuarded":0},"champExperience":20239,"champLevel":18,"championId":127,"championName":"Lissandra","championTransform":0,"consumablesPurchased":4,"damageDealtToBuildings":1929,"damageDealtToObjectives":11298,"damageDealtToTurrets":1929,"damageSelfMitigated":18210,"deaths":9,"detectorWardsPlaced":2,"doubleKills":2,"dragonKills":0,"eligibleForProgression":true,"firstBloodAssist":false,"firstBloodKill":false,"firstTowerAssist":false,"firstTowerKill":false,"gameEndedInEarlySurrender":false,"gameEndedInSurrender":false,"goldEarned":15616,"goldSpent":14900,"individualPosition":"MIDDLE","inhibitorKills":0,"inhibitorTakedowns":1,"inhibitorsLost":1,"item0":3157,"item1":3020,"item2":3135,"item3":7012,"item4":3089,"item5":3916,"item6":3364,"itemsPurchased":26,"killingSprees":2,"kills":9,"lane":"TOP","largestCriticalStrike":0,"largestKillingSpree":4,"largestMultiKill":2,"longestTimeSpentLiving":480,"magicDamageDealt":206345,"magicDamageDealtToChampions":44363,"magicDamageTaken":14669,"neutralMinionsKilled":13,"nexusKills":0,"nexusLost":0,"nexusTakedowns":1,"objectivesStolen":0,"objectivesStolenAssists":0,"participantId":8,"pentaKills":0,"perks":{"statPerks":{"defense":5003,"flex":5008,"offense":5005},"styles":[{"description":"primaryStyle","selections":[{"perk":8360,"var1":13,"var2":0,"var3":0},{"perk":8313,"var1":0,"var2":0,"var3":0},{"perk":8316,"var1":6072,"var2":0,"var3":0},{"perk":8347,"var1":0,"var2":0,"var3":0}],"style":8300},{"description":"subStyle","selections":[{"perk":8226,"var1":250,"var2":1656,"var3":0},{"perk":8210,"var1":21,"var2":0,"var3":0}],"style":8200}]},"physicalDamageDealt":12971,"physicalDamageDealtToChampions":1557,"physicalDamageTaken":10899,"profileIcon":4629,"puuid":"nGVbXWThRhM1jk6MzeAa-0ULFRQBRoSFSXLty8aWR8KipJ2-w82FRTaJHs38TWCpUCgHzbR4b03S9A","quadraKills":0,"riotIdName":"","riotIdTagline":"","role":"DUO","sightWardsBoughtInGame":0,"spell1Casts":153,"spell2Casts":68,"spell3Casts":86,"spell4Casts":24,"summoner1Casts":10,"summoner1Id":12,"summoner2Casts":7,"summoner2Id":4,"summonerId":"fOWYeMy2dE_jGaBF0wXN8rt8zSsj10GcUxI2EsX6DzYWlWFi","summonerLevel":990,"summonerName":"Ribu1","teamEarlySurrendered":false,"teamId":200,"teamPosition":"MIDDLE","timeCCingOthers":62,"timePlayed":2188,"totalDamageDealt":226442,"totalDamageDealtToChampions":47833,"totalDamageShieldedOnTeammates":0,"totalDamageTaken":29890,"totalHeal":4336,"totalHealsOnTeammates":0,"totalMinionsKilled":280,"totalTimeCCDealt":408,"totalTimeSpentDead":404,"totalUnitsHealed":1,"tripleKills":0,"trueDamageDealt":7124,"trueDamageDealtToChampions":1913,"trueDamageTaken":4322,"turretKills":1,"turretTakedowns":1,"turretsLost":8,"unrealKills":0,"visionScore":22,"visionWardsBoughtInGame":2,"wardsKilled":4,"wardsPlaced":4,"win":true},{"assists":21,"baronKills":0,"basicPings":86,"bountyLevel":0,"challenges":{"12AssistStreakCount":0,"abilityUses":209,"acesBefore15Minutes":0,"alliedJungleMonsterKills":10.000000029802322,"baronBuffGoldAdvantageOverThreshold":1,"baronTakedowns":2,"blastConeOppositeOpponentCount":0,"bountyGold":600,"buffsStolen":0,"completeSupportQuestInTime":1,"controlWardTimeCoverageInRiverOrEnemyHalf":0.00395446577770235,"controlWardsPlaced":1,"damagePerMinute":1031.2335207081671,"damageTakenOnTeamPercentage":0.16760947646349228,"dancedWithRiftHerald":0,"deathsByEnemyChamps":12,"dodgeSkillShotsSmallWindow":49,"doubleAces":0,"dragonTakedowns":1,"earliestBaron":1723.2915894011035,"earliestDragonTakedown":1071.3877986176212,"earlyLaningPhaseGoldExpAdvantage":0,"effectiveHealAndShielding":6220.1611328125,"elderDragonKillsWithOpposingSoul":0,"elderDragonMultikills":0,"enemyChampionImmobilizations":29,"enemyJungleMonsterKills":0,"epicMonsterKillsNearEnemyJungler":0,"epicMonsterKillsWithin30SecondsOfSpawn":0,"epicMonsterSteals":0,"epicMonsterStolenWithoutSmite":0,"fasterSupportQuestCompletion":1,"flawlessAces":2,"fullTeamTakedown":1,"gameLength":2188.924978844632,"getTakedownsInAllLanesEarlyJungleAsLaner":0,"goldPerMinute":388.12973638248343,"hadOpenNexus":0,"immobilizeAndKillWithAlly":4,"initialBuffCount":0,"initialCrabCount":0,"jungleCsBefore10Minutes":0,"junglerTakedownsNearDamagedEpicMonster":0,"kTurretsDestroyedBeforePlatesFall":0,"kda":2.3333333333333335,"killAfterHiddenWithAlly":2,"killParticipation":0.5384615384615384,"killedChampTookFullTeamDamageSurvived":0,"killingSprees":1,"killsNearEnemyTurret":2,"killsOnOtherLanesEarlyJungleAsLaner":0,"killsOnRecentlyHealedByAramPack":0,"killsUnderOwnTurret":1,"killsWithHelpFromEpicMonster":0,"knockEnemyIntoTeamAndKill":0,"landSkillShotsEarlyGame":8,"laneMinionsFirst10Minutes":6,"laningPhaseGoldExpAdvantage":0,"legendaryCount":0,"lostAnInhibitor":1,"maxCsAdvantageOnLaneOpponent":15.750000029802322,"maxKillDeficit":3,"maxLevelLeadLaneOpponent":2,"moreEnemyJungleThanOpponent":-119.40000006556511,"multiKillOneSpell":0,"multiTurretRiftHeraldCount":0,"multikills":0,"multikillsAfterAggressiveFlash":0,"outerTurretExecutesBefore10Minutes":0,"outnumberedKills":1,"outnumberedNexusKill":0,"perfectDragonSoulsTaken":1,"perfectGame":0,"pickKillWithAlly":18,"poroExplosions":0,"quickCleanse":0,"quickFirstTurret":0,"quickSoloKills":0,"riftHeraldTakedowns":0,"saveAllyFromDeath":0,"scuttleCrabKills":1,"shortestTimeToAceFromFirstTakedown":39.097569014399596,"skillshotsDodged":246,"skillshotsHit":44,"snowballsHit":0,"soloBaronKills":0,"soloKills":1,"stealthWardsPlaced":40,"survivedSingleDigitHpCount":0,"survivedThreeImmobilizesInFight":0,"takedownOnFirstTurret":0,"takedowns":28,"takedownsAfterGainingLevelAdvantage":0,"takedownsBeforeJungleMinionSpawn":0,"takedownsFirstXMinutes":5,"takedownsInAlcove":0,"takedownsInEnemyFountain":0,"teamBaronKills":2,"teamDamagePercentage":0.18376669661131595,"teamElderDragonKills":0,"teamRiftHeraldKills":0,"threeWardsOneSweeperCount":0,"tookLargeDamageSurvived":0,"turretPlatesTaken":3,"turretTakedowns":3,"turretsTakenWithRiftHerald":0,"twentyMinionsIn3SecondsCount":1,"unseenRecalls":0,"visionScoreAdvantageLaneOpponent":-0.30399662256240845,"visionScorePerMinute":1.7939710218071194,"wardTakedowns":5,"wardTakedownsBefore20M":2,"wardsGuarded":2},"champExperience":16438,"champLevel":16,"championId":235,"championName":"Senna","championTransform":0,"consumablesPurchased":7,"damageDealtToBuildings":2828,"damageDealtToObjectives":9996,"damageDealtToTurrets":2828,"damageSelfMitigated":15444,"deaths":12,"detectorWardsPlaced":1,"doubleKills":0,"dragonKills":0,"eligibleForProgression":true,"firstBloodAssist":false,"firstBloodKill":false,"firstTowerAssist":false,"firstTowerKill":false,"gameEndedInEarlySurrender":false,"gameEndedInSurrender":false,"goldEarned":14159,"goldSpent":13975,"individualPosition":"UTILITY","inhibitorKills":1,"inhibitorTakedowns":1,"inhibitorsLost":1,"item0":3036,"item1":3864,"item2":3094,"item3":3006,"item4":7007,"item5":3124,"item6":3364,"itemsPurchased":32,"killingSprees":2,"kills":7,"lane":"BOTTOM","largestCriticalStrike":313,"largestKillingSpree":3,"largestMultiKill":1,"longestTimeSpentLiving":300,"magicDamageDealt":1848,"magicDamageDealtToChampions":758,"magicDamageTaken":16517,"neutralMinionsKilled":14,"nexusKills":0,"nexusLost":0,"nexusTakedowns":0,"objectivesStolen":0,"objectivesStolenAssists":0,"participantId":9,"pentaKills":0,"perks":{"statPerks":{"defense":5002,"flex":5008,"offense":5005},"styles":[{"description":"primaryStyle","selections":[{"perk":8021,"var1":3915,"var2":3074,"var3":0},{"perk":8009,"var1":4152,"var2":0,"var3":0},{"perk":9103,"var1":22,"var2":40,"var3":0},{"perk":8017,"var1":3394,"var2":0,"var3":0}],"style":8000},{"description":"subStyle","selections":[{"perk":8345,"var1":3,"var2":0,"var3":0},{"perk":8410,"var1":113,"var2":0,"var3":0}],"style":8300}]},"physicalDamageDealt":94292,"physicalDamageDealtToChampions":31765,"physicalDamageTaken":14247,"profileIcon":10,"puuid":"gunnoWXJDEoUg0UbOCWMN1AuSQ-2YJvBFKwJjVYOEJ9oeC1091F37FeVzCvRZBzPGG-q6py1bGq6Bw","quadraKills":0,"riotIdName":"","riotIdTagline":"","role":"SUPPORT","sightWardsBoughtInGame":0,"spell1Casts":92,"spell2Casts":68,"spell3Casts":38,"spell4Casts":11,"summoner1Casts":6,"summoner1Id":4,"summoner2Casts":7,"summoner2Id":7,"summonerId":"Kkiwkjk5ZKDmrogcmbzEDS_P-w9_ZozXkMNNjfa-kFaxKXA3","summonerLevel":343,"summonerName":"Pengedans","teamEarlySurrendered":false,"teamId":200,"teamPosition":"UTILITY","timeCCingOthers":51,"timePlayed":2188,"totalDamageDealt":105826,"totalDamageDealtToChampions":37621,"totalDamageShieldedOnTeammates":2414,"totalDamageTaken":33156,"totalHeal":14771,"totalHealsOnTeammates":3805,"totalMinionsKilled":40,"totalTimeCCDealt":374,"totalTimeSpentDead":409,"totalUnitsHealed":6,"tripleKills":0,"trueDamageDealt":9685,"trueDamageDealtToChampions":5097,"trueDamageTaken":2390,"turretKills":1,"turretTakedowns":3,"turretsLost":8,"unrealKills":0,"visionScore":65,"visionWardsBoughtInGame":4,"wardsKilled":5,"wardsPlaced":41,"win":true},{"assists":17,"baronKills":0,"basicPings":70,"bountyLevel":2,"challenges":{"12AssistStreakCount":0,"abilityUses":327,"acesBefore15Minutes":0,"alliedJungleMonsterKills":28,"baronBuffGoldAdvantageOverThreshold":1,"baronTakedowns":1,"blastConeOppositeOpponentCount":0,"bountyGold":1100,"buffsStolen":0,"completeSupportQuestInTime":0,"controlWardTimeCoverageInRiverOrEnemyHalf":0.0666987099086033,"controlWardsPlaced":1,"damagePerMinute":796.3157113235274,"damageTakenOnTeamPercentage":0.22548120640595076,"dancedWithRiftHerald":0,"deathsByEnemyChamps":12,"dodgeSkillShotsSmallWindow":46,"doubleAces":0,"dragonTakedowns":4,"earliestBaron":1723.2915894011035,"earliestDragonTakedown":413.1778313029502,"earlyLaningPhaseGoldExpAdvantage":0,"effectiveHealAndShielding":0,"elderDragonKillsWithOpposingSoul":0,"elderDragonMultikills":0,"enemyChampionImmobilizations":30,"enemyJungleMonsterKills":0,"epicMonsterKillsNearEnemyJungler":0,"epicMonsterKillsWithin30SecondsOfSpawn":0,"epicMonsterSteals":0,"epicMonsterStolenWithoutSmite":0,"flawlessAces":2,"fullTeamTakedown":1,"gameLength":2188.924978844632,"getTakedownsInAllLanesEarlyJungleAsLaner":0,"goldPerMinute":504.884287404097,"hadOpenNexus":0,"immobilizeAndKillWithAlly":10,"initialBuffCount":0,"initialCrabCount":0,"jungleCsBefore10Minutes":0,"junglerTakedownsNearDamagedEpicMonster":0,"kTurretsDestroyedBeforePlatesFall":0,"kda":2.25,"killAfterHiddenWithAlly":0,"killParticipation":0.5192307692307693,"killedChampTookFullTeamDamageSurvived":0,"killingSprees":1,"killsNearEnemyTurret":2,"killsOnOtherLanesEarlyJungleAsLaner":0,"killsOnRecentlyHealedByAramPack":0,"killsUnderOwnTurret":0,"killsWithHelpFromEpicMonster":0,"knockEnemyIntoTeamAndKill":0,"landSkillShotsEarlyGame":0,"laneMinionsFirst10Minutes":57,"laningPhaseGoldExpAdvantage":0,"legendaryCount":0,"lostAnInhibitor":1,"maxCsAdvantageOnLaneOpponent":25,"maxKillDeficit":3,"maxLevelLeadLaneOpponent":1,"moreEnemyJungleThanOpponent":-119.40000006556511,"multiKillOneSpell":0,"multiTurretRiftHeraldCount":0,"multikills":2,"multikillsAfterAggressiveFlash":0,"outerTurretExecutesBefore10Minutes":0,"outnumberedKills":4,"outnumberedNexusKill":0,"perfectDragonSoulsTaken":1,"perfectGame":0,"pickKillWithAlly":13,"poroExplosions":0,"quickCleanse":0,"quickFirstTurret":0,"quickSoloKills":0,"riftHeraldTakedowns":0,"saveAllyFromDeath":0,"scuttleCrabKills":0,"shortestTimeToAceFromFirstTakedown":39.097569014399596,"skillshotsDodged":233,"skillshotsHit":0,"snowballsHit":0,"soloBaronKills":0,"soloKills":0,"soloTurretsLategame":1,"stealthWardsPlaced":7,"survivedSingleDigitHpCount":0,"survivedThreeImmobilizesInFight":4,"takedownOnFirstTurret":0,"takedowns":27,"takedownsAfterGainingLevelAdvantage":1,"takedownsBeforeJungleMinionSpawn":0,"takedownsFirstXMinutes":6,"takedownsInAlcove":0,"takedownsInEnemyFountain":1,"teamBaronKills":2,"teamDamagePercentage":0.14190414177879232,"teamElderDragonKills":0,"teamRiftHeraldKills":0,"threeWardsOneSweeperCount":0,"tookLargeDamageSurvived":0,"turretPlatesTaken":3,"turretTakedowns":5,"turretsTakenWithRiftHerald":0,"twentyMinionsIn3SecondsCount":9,"unseenRecalls":0,"visionScoreAdvantageLaneOpponent":-0.01999068260192871,"visionScorePerMinute":0.6668579022411862,"wardTakedowns":5,"wardTakedownsBefore20M":1,"wardsGuarded":0},"champExperience":20453,"champLevel":18,"championId":62,"championName":"MonkeyKing","championTransform":0,"consumablesPurchased":5,"damageDealtToBuildings":7624,"damageDealtToObjectives":14263,"damageDealtToTurrets":7624,"damageSelfMitigated":40212,"deaths":12,"detectorWardsPlaced":1,"doubleKills":2,"dragonKills":2,"eligibleForProgression":true,"firstBloodAssist":false,"firstBloodKill":false,"firstTowerAssist":false,"firstTowerKill":false,"gameEndedInEarlySurrender":false,"gameEndedInSurrender":false,"goldEarned":18419,"goldSpent":16450,"individualPosition":"BOTTOM","inhibitorKills":1,"inhibitorTakedowns":1,"inhibitorsLost":1,"item0":7017,"item1":1037,"item2":3074,"item3":6333,"item4":3071,"item5":3047,"item6":3364,"itemsPurchased":32,"killingSprees":3,"kills":10,"lane":"BOTTOM","largestCriticalStrike":0,"largestKillingSpree":4,"largestMultiKill":2,"longestTimeSpentLiving":221,"magicDamageDealt":17845,"magicDamageDealtToChampions":3538,"magicDamageTaken":18888,"neutralMinionsKilled":36,"nexusKills":0,"nexusLost":0,"nexusTakedowns":1,"objectivesStolen":0,"objectivesStolenAssists":0,"participantId":10,"pentaKills":0,"perks":{"statPerks":{"defense":5002,"flex":5008,"offense":5005},"styles":[{"description":"primaryStyle","selections":[{"perk":8010,"var1":1107,"var2":0,"var3":0},{"perk":9111,"var1":1294,"var2":540,"var3":0},{"perk":9105,"var1":12,"var2":30,"var3":0},{"perk":8299,"var1":973,"var2":0,"var3":0}],"style":8000},{"description":"subStyle","selections":[{"perk":8316,"var1":4213,"var2":0,"var3":0},{"perk":8347,"var1":0,"var2":0,"var3":0}],"style":8300}]},"physicalDamageDealt":145344,"physicalDamageDealtToChampions":23974,"physicalDamageTaken":16922,"profileIcon":4410,"puuid":"9Z1JFDSeOnHsvZC0DIAWh_wP3XkdZiHYy_yf8vxIOHS29gol_x4z7_DiCzjbnxao5Wqp5fnPzm6LfQ","quadraKills":0,"riotIdName":"","riotIdTagline":"","role":"CARRY","sightWardsBoughtInGame":0,"spell1Casts":150,"spell2Casts":58,"spell3Casts":91,"spell4Casts":28,"summoner1Casts":5,"summoner1Id":4,"summoner2Casts":5,"summoner2Id":14,"summonerId":"218HsfDdA23sQzkn3Qfq7NjjPDWEDSd4kx-YhVQwF3p6NUo","summonerLevel":454,"summonerName":"INT Baul","teamEarlySurrendered":false,"teamId":200,"teamPosition":"BOTTOM","timeCCingOthers":22,"timePlayed":2188,"totalDamageDealt":173828,"totalDamageDealtToChampions":29051,"totalDamageShieldedOnTeammates":0,"totalDamageTaken":44604,"totalHeal":15912,"totalHealsOnTeammates":0,"totalMinionsKilled":190,"totalTimeCCDealt":149,"totalTimeSpentDead":389,"totalUnitsHealed":1,"tripleKills":0,"trueDamageDealt":10638,"trueDamageDealtToChampions":1539,"trueDamageTaken":8793,"turretKills":4,"turretTakedowns":5,"turretsLost":8,"unrealKills":0,"visionScore":24,"visionWardsBoughtInGame":1,"wardsKilled":5,"wardsPlaced":8,"win":true}],"platformId":"EUW1","queueId":420,"teams":[{"bans":[{"championId":134,"pickTurn":1},{"championId":24,"pickTurn":2},{"championId":76,"pickTurn":3},{"championId":360,"pickTurn":4},{"championId":119,"pickTurn":5}],"objectives":{"baron":{"first":false,"kills":0},"champion":{"first":false,"kills":49},"dragon":{"first":false,"kills":1},"inhibitor":{"first":false,"kills":1},"riftHerald":{"first":true,"kills":2},"tower":{"first":true,"kills":8}},"teamId":100,"win":false},{"bans":[{"championId":266,"pickTurn":6},{"championId":200,"pickTurn":7},{"championId":107,"pickTurn":8},{"championId":350,"pickTurn":9},{"championId":32,"pickTurn":10}],"objectives":{"baron":{"first":true,"kills":2},"champion":{"first":true,"kills":52},"dragon":{"first":true,"kills":4},"inhibitor":{"first":true,"kills":2},"riftHerald":{"first":false,"kills":0},"tower":{"first":false,"kills":8}},"teamId":200,"win":true}],"tournamentCode":""}}